<?xml version="1.0"?>
<!-- edited with XMLSpy v2014 rel. 2 sp1 (http://www.altova.com) by Soren Johnson (private) -->
<Root>
	<Entry>
		<zType/>
		<Name/>
		<zFieldName/>
		<zISOCode/>
		<iExportColumn/>
		<bPublicBuild/>
		<bDebug/>
		<zSingularExpression/>
		<zPluralExpression/>
		<zThousandsSeparator/>
		<zDecimalSeparator/>
		<zCurrencyPrefix/>
		<zCurrencyPostfix/>
		<zThousandPostfix/>
		<zMillionPostfix/>
	</Entry>
	<Entry>
		<zType>LANGUAGE_ENGLISH</zType>
		<Name>TEXT_LANGUAGE_ENGLISH</Name>
		<zFieldName>English</zFieldName>
		<zISOCode>en</zISOCode>
		<iExportColumn>3</iExportColumn>
		<bPublicBuild>1</bPublicBuild>
		<zSingularExpression>x==1</zSingularExpression>
		<zThousandsSeparator>,</zThousandsSeparator>
		<zDecimalSeparator>.</zDecimalSeparator>
		<zCurrencyPrefix>$</zCurrencyPrefix>
		<zThousandPostfix>K</zThousandPostfix>
		<zMillionPostfix>M</zMillionPostfix>
	</Entry>
	<Entry>
		<zType>LANGUAGE_DEBUG</zType>
		<Name>TEXT_LANGUAGE_DEBUG</Name>
		<zISOCode>en</zISOCode>
		<iExportColumn>3</iExportColumn>
		<bPublicBuild>0</bPublicBuild>
		<bDebug>1</bDebug>
		<zSingularExpression>x==1</zSingularExpression>
		<zThousandsSeparator>,</zThousandsSeparator>
		<zDecimalSeparator>.</zDecimalSeparator>
		<zCurrencyPrefix>$</zCurrencyPrefix>
		<zThousandPostfix>K</zThousandPostfix>
		<zMillionPostfix>M</zMillionPostfix>
	</Entry>
	<Entry>
		<zType>LANGUAGE_TRANSLATION</zType>
		<zFieldName>Translation</zFieldName>
		<bPublicBuild>1</bPublicBuild>
		<zSingularExpression>x==1</zSingularExpression>
		<zThousandsSeparator>,</zThousandsSeparator>
		<zDecimalSeparator>.</zDecimalSeparator>
		<zCurrencyPrefix>$</zCurrencyPrefix>
		<zThousandPostfix>K</zThousandPostfix>
		<zMillionPostfix>M</zMillionPostfix>
	</Entry>
</Root>
